{
  "data": {
    "id": "01982ca2-4a93-8681-7469-b13e182384f7",
    "name": "Singapore",
    "name_id": "Singapura",
    "slug": "singapore",
    "description": null,
    "description_id": null,
    "scale": "local",
    "is_saleable": true,
    "area_color": "FFE3ED",
    "area_code": "SG",
    "total_countries": 1,
    "details": [
      {
        "text": "Tethering / Hotspot",
        "value": true
      },
      {
        "text": "Best Network",
        "value": true
      },
      {
        "text": "3G, 4G, and 5G",
        "value": true
      },
      {
        "text": "Auto APN",
        "value": true
      },
      {
        "text": "No eKYC / ID Registration",
        "value": true
      },
      {
        "text": "Rechargeable",
        "value": true
      }
    ],
    "product_items": [
      {
        "natural_name": "Singapore 07D 03GB",
        "validity_days": 7,
        "data_type": "limited",
        "quota_in_gb": 3,
        "prices": [
          {
            "currency_code": "IDR",
            "is_recommended": false,
            "standard": {
              "id": "01982ded-f1cb-ebe2-f3b9-ca604e5f8ade",
              "price": 55000,
              "discounted_price": 55000,
              "discount_percentage": null
            },
            "premium": null
          },
          {
            "currency_code": "USD",
            "is_recommended": false,
            "standard": {
              "id": "01982ded-f1cb-ebe2-f3b9-ca604e5f8ade",
              "price": 4.5,
              "discounted_price": 4.5,
              "discount_percentage": null
            },
            "premium": null
          }
        ],
        "is_recommended": false,
        "standard": {
          "id": "01982ded-f1cb-ebe2-f3b9-ca604e5f8ade",
          "currency_code": "IDR",
          "price": 55000,
          "discounted_price": 55000,
          "discount_percentage": null
        },
        "premium": null
      },
      {
        "natural_name": "Singapore 10D 03GB",
        "validity_days": 10,
        "data_type": "limited",
        "quota_in_gb": 3,
        "prices": [
          {
            "currency_code": "IDR",
            "is_recommended": false,
            "standard": {
              "id": "01982ded-f1cc-2efb-00cd-e40352867925",
              "price": 65000,
              "discounted_price": 65000,
              "discount_percentage": null
            },
            "premium": null
          },
          {
            "currency_code": "USD",
            "is_recommended": false,
            "standard": {
              "id": "01982ded-f1cc-2efb-00cd-e40352867925",
              "price": 5,
              "discounted_price": 5,
              "discount_percentage": null
            },
            "premium": null
          }
        ],
        "is_recommended": false,
        "standard": {
          "id": "01982ded-f1cc-2efb-00cd-e40352867925",
          "currency_code": "IDR",
          "price": 65000,
          "discounted_price": 65000,
          "discount_percentage": null
        },
        "premium": null
      },
      {
        "natural_name": "Singapore 01D 05GB",
        "validity_days": 1,
        "data_type": "limited",
        "quota_in_gb": 5,
        "prices": [
          {
            "currency_code": "IDR",
            "is_recommended": false,
            "standard": {
              "id": "01982ded-f1ce-bc31-63cc-f6e5a3955a07",
              "price": 57000,
              "discounted_price": 57000,
              "discount_percentage": null
            },
            "premium": null
          },
          {
            "currency_code": "USD",
            "is_recommended": false,
            "standard": {
              "id": "01982ded-f1ce-bc31-63cc-f6e5a3955a07",
              "price": 4.5,
              "discounted_price": 4.5,
              "discount_percentage": null
            },
            "premium": null
          }
        ],
        "is_recommended": false,
        "standard": {
          "id": "01982ded-f1ce-bc31-63cc-f6e5a3955a07",
          "currency_code": "IDR",
          "price": 57000,
          "discounted_price": 57000,
          "discount_percentage": null
        },
        "premium": null
      },
      {
        "natural_name": "Singapore 03D 05GB",
        "validity_days": 3,
        "data_type": "limited",
        "quota_in_gb": 5,
        "prices": [
          {
            "currency_code": "IDR",
            "is_recommended": false,
            "standard": {
              "id": "01982ded-f1ce-bc31-63cc-f6e5a3955a0c",
              "price": 65000,
              "discounted_price": 65000,
              "discount_percentage": null
            },
            "premium": null
          },
          {
            "currency_code": "USD",
            "is_recommended": false,
            "standard": {
              "id": "01982ded-f1ce-bc31-63cc-f6e5a3955a0c",
              "price": 5,
              "discounted_price": 5,
              "discount_percentage": null
            },
            "premium": null
          }
        ],
        "is_recommended": false,
        "standard": {
          "id": "01982ded-f1ce-bc31-63cc-f6e5a3955a0c",
          "currency_code": "IDR",
          "price": 65000,
          "discounted_price": 65000,
          "discount_percentage": null
        },
        "premium": null
      },
      {
        "natural_name": "Singapore 15D 05GB",
        "validity_days": 15,
        "data_type": "limited",
        "quota_in_gb": 5,
        "prices": [
          {
            "currency_code": "IDR",
            "is_recommended": false,
            "standard": {
              "id": "01982ded-f1d2-ae37-5da9-2a6712f0a763",
              "price": 107000,
              "discounted_price": 107000,
              "discount_percentage": null
            },
            "premium": null
          },
          {
            "currency_code": "USD",
            "is_recommended": false,
            "standard": {
              "id": "01982ded-f1d2-ae37-5da9-2a6712f0a763",
              "price": 7.5,
              "discounted_price": 7.5,
              "discount_percentage": null
            },
            "premium": null
          }
        ],
        "is_recommended": false,
        "standard": {
          "id": "01982ded-f1d2-ae37-5da9-2a6712f0a763",
          "currency_code": "IDR",
          "price": 107000,
          "discounted_price": 107000,
          "discount_percentage": null
        },
        "premium": null
      },
      {
        "natural_name": "Singapore 03D 10GB",
        "validity_days": 3,
        "data_type": "limited",
        "quota_in_gb": 10,
        "prices": [
          {
            "currency_code": "IDR",
            "is_recommended": false,
            "standard": {
              "id": "01982ded-f1d3-8937-d5f5-2f413fb919e5",
              "price": 103000,
              "discounted_price": 103000,
              "discount_percentage": null
            },
            "premium": null
          },
          {
            "currency_code": "USD",
            "is_recommended": false,
            "standard": {
              "id": "01982ded-f1d3-8937-d5f5-2f413fb919e5",
              "price": 8,
              "discounted_price": 8,
              "discount_percentage": null
            },
            "premium": null
          }
        ],
        "is_recommended": false,
        "standard": {
          "id": "01982ded-f1d3-8937-d5f5-2f413fb919e5",
          "currency_code": "IDR",
          "price": 103000,
          "discounted_price": 103000,
          "discount_percentage": null
        },
        "premium": null
      },
      {
        "natural_name": "Singapore 07D 10GB",
        "validity_days": 7,
        "data_type": "limited",
        "quota_in_gb": 10,
        "prices": [
          {
            "currency_code": "IDR",
            "is_recommended": false,
            "standard": {
              "id": "01982ded-f1d4-993a-b8ad-021fb05ffa96",
              "price": 116000,
              "discounted_price": 116000,
              "discount_percentage": null
            },
            "premium": null
          },
          {
            "currency_code": "USD",
            "is_recommended": false,
            "standard": {
              "id": "01982ded-f1d4-993a-b8ad-021fb05ffa96",
              "price": 8.5,
              "discounted_price": 8.5,
              "discount_percentage": null
            },
            "premium": null
          }
        ],
        "is_recommended": false,
        "standard": {
          "id": "01982ded-f1d4-993a-b8ad-021fb05ffa96",
          "currency_code": "IDR",
          "price": 116000,
          "discounted_price": 116000,
          "discount_percentage": null
        },
        "premium": null
      },
      {
        "natural_name": "Singapore 07D 20GB",
        "validity_days": 7,
        "data_type": "limited",
        "quota_in_gb": 20,
        "prices": [
          {
            "currency_code": "IDR",
            "is_recommended": false,
            "standard": {
              "id": "01982ded-f1d9-2182-f79f-5368e16a1270",
              "price": 173000,
              "discounted_price": 173000,
              "discount_percentage": null
            },
            "premium": null
          },
          {
            "currency_code": "USD",
            "is_recommended": false,
            "standard": {
              "id": "01982ded-f1d9-2182-f79f-5368e16a1270",
              "price": 12.5,
              "discounted_price": 12.5,
              "discount_percentage": null
            },
            "premium": null
          }
        ],
        "is_recommended": false,
        "standard": {
          "id": "01982ded-f1d9-2182-f79f-5368e16a1270",
          "currency_code": "IDR",
          "price": 173000,
          "discounted_price": 173000,
          "discount_percentage": null
        },
        "premium": null
      },
      {
        "natural_name": "Singapore 10D 20GB",
        "validity_days": 10,
        "data_type": "limited",
        "quota_in_gb": 20,
        "prices": [
          {
            "currency_code": "IDR",
            "is_recommended": false,
            "standard": {
              "id": "01982ded-f1db-86ff-d50f-ce8043a3c2df",
              "price": 216000,
              "discounted_price": 216000,
              "discount_percentage": null
            },
            "premium": null
          },
          {
            "currency_code": "USD",
            "is_recommended": false,
            "standard": {
              "id": "01982ded-f1db-86ff-d50f-ce8043a3c2df",
              "price": 15,
              "discounted_price": 15,
              "discount_percentage": null
            },
            "premium": null
          }
        ],
        "is_recommended": false,
        "standard": {
          "id": "01982ded-f1db-86ff-d50f-ce8043a3c2df",
          "currency_code": "IDR",
          "price": 216000,
          "discounted_price": 216000,
          "discount_percentage": null
        },
        "premium": null
      },
      {
        "natural_name": "Singapore 15D 20GB",
        "validity_days": 15,
        "data_type": "limited",
        "quota_in_gb": 20,
        "prices": [
          {
            "currency_code": "IDR",
            "is_recommended": false,
            "standard": {
              "id": "01982ded-f1dc-0153-8213-7ccc2911664b",
              "price": 253000,
              "discounted_price": 253000,
              "discount_percentage": null
            },
            "premium": null
          },
          {
            "currency_code": "USD",
            "is_recommended": false,
            "standard": {
              "id": "01982ded-f1dc-0153-8213-7ccc2911664b",
              "price": 17.5,
              "discounted_price": 17.5,
              "discount_percentage": null
            },
            "premium": null
          }
        ],
        "is_recommended": false,
        "standard": {
          "id": "01982ded-f1dc-0153-8213-7ccc2911664b",
          "currency_code": "IDR",
          "price": 253000,
          "discounted_price": 253000,
          "discount_percentage": null
        },
        "premium": null
      },
      {
        "natural_name": "Singapore 30D 20GB",
        "validity_days": 30,
        "data_type": "limited",
        "quota_in_gb": 20,
        "prices": [
          {
            "currency_code": "IDR",
            "is_recommended": false,
            "standard": {
              "id": "01982ded-f1de-accc-1420-662d7ed93be9",
              "price": 284000,
              "discounted_price": 284000,
              "discount_percentage": null
            },
            "premium": null
          },
          {
            "currency_code": "USD",
            "is_recommended": false,
            "standard": {
              "id": "01982ded-f1de-accc-1420-662d7ed93be9",
              "price": 19.5,
              "discounted_price": 19.5,
              "discount_percentage": null
            },
            "premium": null
          }
        ],
        "is_recommended": false,
        "standard": {
          "id": "01982ded-f1de-accc-1420-662d7ed93be9",
          "currency_code": "IDR",
          "price": 284000,
          "discounted_price": 284000,
          "discount_percentage": null
        },
        "premium": null
      },
      {
        "natural_name": "Singapore 10D 30GB",
        "validity_days": 10,
        "data_type": "limited",
        "quota_in_gb": 30,
        "prices": [
          {
            "currency_code": "IDR",
            "is_recommended": false,
            "standard": {
              "id": "01982ded-f1df-1ce9-d4c8-64b58252b60d",
              "price": 295000,
              "discounted_price": 295000,
              "discount_percentage": null
            },
            "premium": null
          },
          {
            "currency_code": "USD",
            "is_recommended": false,
            "standard": {
              "id": "01982ded-f1df-1ce9-d4c8-64b58252b60d",
              "price": 20,
              "discounted_price": 20,
              "discount_percentage": null
            },
            "premium": null
          }
        ],
        "is_recommended": false,
        "standard": {
          "id": "01982ded-f1df-1ce9-d4c8-64b58252b60d",
          "currency_code": "IDR",
          "price": 295000,
          "discounted_price": 295000,
          "discount_percentage": null
        },
        "premium": null
      },
      {
        "natural_name": "Singapore 15D 30GB",
        "validity_days": 15,
        "data_type": "limited",
        "quota_in_gb": 30,
        "prices": [
          {
            "currency_code": "IDR",
            "is_recommended": false,
            "standard": {
              "id": "01982ded-f1e0-0acb-98b1-86fb0187934f",
              "price": 312000,
              "discounted_price": 312000,
              "discount_percentage": null
            },
            "premium": null
          },
          {
            "currency_code": "USD",
            "is_recommended": false,
            "standard": {
              "id": "01982ded-f1e0-0acb-98b1-86fb0187934f",
              "price": 21.5,
              "discounted_price": 21.5,
              "discount_percentage": null
            },
            "premium": null
          }
        ],
        "is_recommended": false,
        "standard": {
          "id": "01982ded-f1e0-0acb-98b1-86fb0187934f",
          "currency_code": "IDR",
          "price": 312000,
          "discounted_price": 312000,
          "discount_percentage": null
        },
        "premium": null
      },
      {
        "natural_name": "Singapore 15D FUP1GB PRO",
        "validity_days": 15,
        "data_type": "unlimited",
        "quota_in_gb": 1,
        "prices": [
          {
            "currency_code": "IDR",
            "is_recommended": false,
            "standard": {
              "id": "01982ded-f1ed-6c7a-15a5-a59ef3d9c198",
              "price": 187000,
              "discounted_price": 187000,
              "discount_percentage": null
            },
            "premium": null
          },
          {
            "currency_code": "USD",
            "is_recommended": false,
            "standard": {
              "id": "01982ded-f1ed-6c7a-15a5-a59ef3d9c198",
              "price": 13,
              "discounted_price": 13,
              "discount_percentage": null
            },
            "premium": null
          }
        ],
        "is_recommended": false,
        "standard": {
          "id": "01982ded-f1ed-6c7a-15a5-a59ef3d9c198",
          "currency_code": "IDR",
          "price": 187000,
          "discounted_price": 187000,
          "discount_percentage": null
        },
        "premium": null
      },
      {
        "natural_name": "Singapore 30D FUP1GB PRO",
        "validity_days": 30,
        "data_type": "unlimited",
        "quota_in_gb": 1,
        "prices": [
          {
            "currency_code": "IDR",
            "is_recommended": false,
            "standard": {
              "id": "01982ded-f1ee-5fab-5ff3-347dec699bb5",
              "price": 376000,
              "discounted_price": 376000,
              "discount_percentage": null
            },
            "premium": null
          },
          {
            "currency_code": "USD",
            "is_recommended": false,
            "standard": {
              "id": "01982ded-f1ee-5fab-5ff3-347dec699bb5",
              "price": 25.5,
              "discounted_price": 25.5,
              "discount_percentage": null
            },
            "premium": null
          }
        ],
        "is_recommended": false,
        "standard": {
          "id": "01982ded-f1ee-5fab-5ff3-347dec699bb5",
          "currency_code": "IDR",
          "price": 376000,
          "discounted_price": 376000,
          "discount_percentage": null
        },
        "premium": null
      },
      {
        "natural_name": "Singapore 10D FUP2GB ELITE",
        "validity_days": 10,
        "data_type": "unlimited",
        "quota_in_gb": 2,
        "prices": [
          {
            "currency_code": "IDR",
            "is_recommended": false,
            "standard": {
              "id": "01982ded-f1f2-ace2-b80a-a4d301694962",
              "price": 222000,
              "discounted_price": 222000,
              "discount_percentage": null
            },
            "premium": null
          },
          {
            "currency_code": "USD",
            "is_recommended": false,
            "standard": {
              "id": "01982ded-f1f2-ace2-b80a-a4d301694962",
              "price": 15.5,
              "discounted_price": 15.5,
              "discount_percentage": null
            },
            "premium": null
          }
        ],
        "is_recommended": false,
        "standard": {
          "id": "01982ded-f1f2-ace2-b80a-a4d301694962",
          "currency_code": "IDR",
          "price": 222000,
          "discounted_price": 222000,
          "discount_percentage": null
        },
        "premium": null
      },
      {
        "natural_name": "Singapore 15D FUP2GB ELITE",
        "validity_days": 15,
        "data_type": "unlimited",
        "quota_in_gb": 2,
        "prices": [
          {
            "currency_code": "IDR",
            "is_recommended": false,
            "standard": {
              "id": "01982ded-f1f3-f846-ef3f-453fea8f4617",
              "price": 330000,
              "discounted_price": 330000,
              "discount_percentage": null
            },
            "premium": null
          },
          {
            "currency_code": "USD",
            "is_recommended": false,
            "standard": {
              "id": "01982ded-f1f3-f846-ef3f-453fea8f4617",
              "price": 22.5,
              "discounted_price": 22.5,
              "discount_percentage": null
            },
            "premium": null
          }
        ],
        "is_recommended": false,
        "standard": {
          "id": "01982ded-f1f3-f846-ef3f-453fea8f4617",
          "currency_code": "IDR",
          "price": 330000,
          "discounted_price": 330000,
          "discount_percentage": null
        },
        "premium": null
      },
      {
        "natural_name": "Singapore 30D FUP2GB ELITE",
        "validity_days": 30,
        "data_type": "unlimited",
        "quota_in_gb": 2,
        "prices": [
          {
            "currency_code": "IDR",
            "is_recommended": false,
            "standard": {
              "id": "01982ded-f1f5-eebc-69da-cf4c2aad1515",
              "price": 546000,
              "discounted_price": 546000,
              "discount_percentage": null
            },
            "premium": null
          },
          {
            "currency_code": "USD",
            "is_recommended": false,
            "standard": {
              "id": "01982ded-f1f5-eebc-69da-cf4c2aad1515",
              "price": 37,
              "discounted_price": 37,
              "discount_percentage": null
            },
            "premium": null
          }
        ],
        "is_recommended": false,
        "standard": {
          "id": "01982ded-f1f5-eebc-69da-cf4c2aad1515",
          "currency_code": "IDR",
          "price": 546000,
          "discounted_price": 546000,
          "discount_percentage": null
        },
        "premium": null
      },
      {
        "natural_name": "Singapore 03D 01GB",
        "validity_days": 3,
        "data_type": "limited",
        "quota_in_gb": 1,
        "prices": [
          {
            "currency_code": "IDR",
            "is_recommended": false,
            "standard": {
              "id": "01982ded-f1c8-95b2-e226-5d4bb44a9184",
              "price": 28000,
              "discounted_price": 28000,
              "discount_percentage": null
            },
            "premium": null
          },
          {
            "currency_code": "USD",
            "is_recommended": false,
            "standard": {
              "id": "01982ded-f1c8-95b2-e226-5d4bb44a9184",
              "price": 2.5,
              "discounted_price": 2.5,
              "discount_percentage": null
            },
            "premium": null
          }
        ],
        "is_recommended": false,
        "standard": {
          "id": "01982ded-f1c8-95b2-e226-5d4bb44a9184",
          "currency_code": "IDR",
          "price": 28000,
          "discounted_price": 28000,
          "discount_percentage": null
        },
        "premium": null
      },
      {
        "natural_name": "Singapore 07D 01GB",
        "validity_days": 7,
        "data_type": "limited",
        "quota_in_gb": 1,
        "prices": [
          {
            "currency_code": "IDR",
            "is_recommended": false,
            "standard": {
              "id": "01982ded-f1c9-80f5-df82-8061f0671943",
              "price": 32000,
              "discounted_price": 32000,
              "discount_percentage": null
            },
            "premium": null
          },
          {
            "currency_code": "USD",
            "is_recommended": false,
            "standard": {
              "id": "01982ded-f1c9-80f5-df82-8061f0671943",
              "price": 3,
              "discounted_price": 3,
              "discount_percentage": null
            },
            "premium": null
          }
        ],
        "is_recommended": false,
        "standard": {
          "id": "01982ded-f1c9-80f5-df82-8061f0671943",
          "currency_code": "IDR",
          "price": 32000,
          "discounted_price": 32000,
          "discount_percentage": null
        },
        "premium": null
      },
      {
        "natural_name": "Singapore 01D 03GB",
        "validity_days": 1,
        "data_type": "limited",
        "quota_in_gb": 3,
        "prices": [
          {
            "currency_code": "IDR",
            "is_recommended": false,
            "standard": {
              "id": "01982ded-f1c9-80f5-df82-8061f0671948",
              "price": 46000,
              "discounted_price": 46000,
              "discount_percentage": null
            },
            "premium": null
          },
          {
            "currency_code": "USD",
            "is_recommended": false,
            "standard": {
              "id": "01982ded-f1c9-80f5-df82-8061f0671948",
              "price": 3.5,
              "discounted_price": 3.5,
              "discount_percentage": null
            },
            "premium": null
          }
        ],
        "is_recommended": false,
        "standard": {
          "id": "01982ded-f1c9-80f5-df82-8061f0671948",
          "currency_code": "IDR",
          "price": 46000,
          "discounted_price": 46000,
          "discount_percentage": null
        },
        "premium": null
      },
      {
        "natural_name": "Singapore 30D 30GB",
        "validity_days": 30,
        "data_type": "limited",
        "quota_in_gb": 30,
        "prices": [
          {
            "currency_code": "IDR",
            "is_recommended": false,
            "standard": {
              "id": "01982ded-f1e2-09c9-b2ff-58566cb6493c",
              "price": 367000,
              "discounted_price": 367000,
              "discount_percentage": null
            },
            "premium": null
          },
          {
            "currency_code": "USD",
            "is_recommended": false,
            "standard": {
              "id": "01982ded-f1e2-09c9-b2ff-58566cb6493c",
              "price": 25,
              "discounted_price": 25,
              "discount_percentage": null
            },
            "premium": null
          }
        ],
        "is_recommended": false,
        "standard": {
          "id": "01982ded-f1e2-09c9-b2ff-58566cb6493c",
          "currency_code": "IDR",
          "price": 367000,
          "discounted_price": 367000,
          "discount_percentage": null
        },
        "premium": null
      },
      {
        "natural_name": "Singapore 01D FUP0.5GB BASIC",
        "validity_days": 1,
        "data_type": "unlimited",
        "quota_in_gb": 0.5,
        "prices": [
          {
            "currency_code": "IDR",
            "is_recommended": false,
            "standard": {
              "id": "01982ded-f1e3-a10b-26b9-5a3cefcd3255",
              "price": 20000,
              "discounted_price": 20000,
              "discount_percentage": null
            },
            "premium": null
          },
          {
            "currency_code": "USD",
            "is_recommended": false,
            "standard": {
              "id": "01982ded-f1e3-a10b-26b9-5a3cefcd3255",
              "price": 2,
              "discounted_price": 2,
              "discount_percentage": null
            },
            "premium": null
          }
        ],
        "is_recommended": false,
        "standard": {
          "id": "01982ded-f1e3-a10b-26b9-5a3cefcd3255",
          "currency_code": "IDR",
          "price": 20000,
          "discounted_price": 20000,
          "discount_percentage": null
        },
        "premium": null
      },
      {
        "natural_name": "Singapore 03D FUP0.5GB BASIC",
        "validity_days": 3,
        "data_type": "unlimited",
        "quota_in_gb": 0.5,
        "prices": [
          {
            "currency_code": "IDR",
            "is_recommended": false,
            "standard": {
              "id": "01982ded-f1e3-a10b-26b9-5a3cefcd325a",
              "price": 30000,
              "discounted_price": 30000,
              "discount_percentage": null
            },
            "premium": null
          },
          {
            "currency_code": "USD",
            "is_recommended": false,
            "standard": {
              "id": "01982ded-f1e3-a10b-26b9-5a3cefcd325a",
              "price": 2.5,
              "discounted_price": 2.5,
              "discount_percentage": null
            },
            "premium": null
          }
        ],
        "is_recommended": false,
        "standard": {
          "id": "01982ded-f1e3-a10b-26b9-5a3cefcd325a",
          "currency_code": "IDR",
          "price": 30000,
          "discounted_price": 30000,
          "discount_percentage": null
        },
        "premium": null
      },
      {
        "natural_name": "Singapore 10D FUP0.5GB BASIC",
        "validity_days": 10,
        "data_type": "unlimited",
        "quota_in_gb": 0.5,
        "prices": [
          {
            "currency_code": "IDR",
            "is_recommended": false,
            "standard": {
              "id": "01982ded-f1e5-5639-a61e-719d0a206f61",
              "price": 98000,
              "discounted_price": 98000,
              "discount_percentage": null
            },
            "premium": null
          },
          {
            "currency_code": "USD",
            "is_recommended": false,
            "standard": {
              "id": "01982ded-f1e5-5639-a61e-719d0a206f61",
              "price": 7,
              "discounted_price": 7,
              "discount_percentage": null
            },
            "premium": null
          }
        ],
        "is_recommended": false,
        "standard": {
          "id": "01982ded-f1e5-5639-a61e-719d0a206f61",
          "currency_code": "IDR",
          "price": 98000,
          "discounted_price": 98000,
          "discount_percentage": null
        },
        "premium": null
      },
      {
        "natural_name": "Singapore 15D FUP0.5GB BASIC",
        "validity_days": 15,
        "data_type": "unlimited",
        "quota_in_gb": 0.5,
        "prices": [
          {
            "currency_code": "IDR",
            "is_recommended": false,
            "standard": {
              "id": "01982ded-f1e6-17db-732a-164ab3603783",
              "price": 122000,
              "discounted_price": 122000,
              "discount_percentage": null
            },
            "premium": null
          },
          {
            "currency_code": "USD",
            "is_recommended": false,
            "standard": {
              "id": "01982ded-f1e6-17db-732a-164ab3603783",
              "price": 8.5,
              "discounted_price": 8.5,
              "discount_percentage": null
            },
            "premium": null
          }
        ],
        "is_recommended": false,
        "standard": {
          "id": "01982ded-f1e6-17db-732a-164ab3603783",
          "currency_code": "IDR",
          "price": 122000,
          "discounted_price": 122000,
          "discount_percentage": null
        },
        "premium": null
      },
      {
        "natural_name": "Singapore 30D FUP0.5GB BASIC",
        "validity_days": 30,
        "data_type": "unlimited",
        "quota_in_gb": 0.5,
        "prices": [
          {
            "currency_code": "IDR",
            "is_recommended": false,
            "standard": {
              "id": "01982ded-f1e7-d7e1-d638-54a98755d432",
              "price": 237000,
              "discounted_price": 237000,
              "discount_percentage": null
            },
            "premium": null
          },
          {
            "currency_code": "USD",
            "is_recommended": false,
            "standard": {
              "id": "01982ded-f1e7-d7e1-d638-54a98755d432",
              "price": 16.5,
              "discounted_price": 16.5,
              "discount_percentage": null
            },
            "premium": null
          }
        ],
        "is_recommended": false,
        "standard": {
          "id": "01982ded-f1e7-d7e1-d638-54a98755d432",
          "currency_code": "IDR",
          "price": 237000,
          "discounted_price": 237000,
          "discount_percentage": null
        },
        "premium": null
      },
      {
        "natural_name": "Singapore 10D 10GB",
        "validity_days": 10,
        "data_type": "limited",
        "quota_in_gb": 10,
        "prices": [
          {
            "currency_code": "IDR",
            "is_recommended": false,
            "standard": {
              "id": "01982ded-f1d5-70fb-f79b-eb72efdb0e67",
              "price": 126000,
              "discounted_price": 126000,
              "discount_percentage": null
            },
            "premium": null
          },
          {
            "currency_code": "USD",
            "is_recommended": false,
            "standard": {
              "id": "01982ded-f1d5-70fb-f79b-eb72efdb0e67",
              "price": 9,
              "discounted_price": 9,
              "discount_percentage": null
            },
            "premium": null
          }
        ],
        "is_recommended": false,
        "standard": {
          "id": "01982ded-f1d5-70fb-f79b-eb72efdb0e67",
          "currency_code": "IDR",
          "price": 126000,
          "discounted_price": 126000,
          "discount_percentage": null
        },
        "premium": null
      },
      {
        "natural_name": "Singapore 07D FUP2GB ELITE",
        "validity_days": 7,
        "data_type": "unlimited",
        "quota_in_gb": 2,
        "prices": [
          {
            "currency_code": "IDR",
            "is_recommended": true,
            "standard": {
              "id": "01982ded-f1f1-667e-a3c2-e5b84a8daba0",
              "price": 157000,
              "discounted_price": 157000,
              "discount_percentage": null
            },
            "premium": null
          },
          {
            "currency_code": "USD",
            "is_recommended": true,
            "standard": {
              "id": "01982ded-f1f1-667e-a3c2-e5b84a8daba0",
              "price": 11,
              "discounted_price": 11,
              "discount_percentage": null
            },
            "premium": null
          }
        ],
        "is_recommended": true,
        "standard": {
          "id": "01982ded-f1f1-667e-a3c2-e5b84a8daba0",
          "currency_code": "IDR",
          "price": 157000,
          "discounted_price": 157000,
          "discount_percentage": null
        },
        "premium": null
      },
      {
        "natural_name": "Singapore 07D FUP1GB PRO",
        "validity_days": 7,
        "data_type": "unlimited",
        "quota_in_gb": 1,
        "prices": [
          {
            "currency_code": "IDR",
            "is_recommended": true,
            "standard": {
              "id": "01982ded-f1eb-5e55-911d-9ce344a9b720",
              "price": 92000,
              "discounted_price": 92000,
              "discount_percentage": null
            },
            "premium": null
          },
          {
            "currency_code": "USD",
            "is_recommended": true,
            "standard": {
              "id": "01982ded-f1eb-5e55-911d-9ce344a9b720",
              "price": 6.5,
              "discounted_price": 6.5,
              "discount_percentage": null
            },
            "premium": null
          }
        ],
        "is_recommended": true,
        "standard": {
          "id": "01982ded-f1eb-5e55-911d-9ce344a9b720",
          "currency_code": "IDR",
          "price": 92000,
          "discounted_price": 92000,
          "discount_percentage": null
        },
        "premium": null
      },
      {
        "natural_name": "Singapore 07D FUP0.5GB BASIC",
        "validity_days": 7,
        "data_type": "unlimited",
        "quota_in_gb": 0.5,
        "prices": [
          {
            "currency_code": "IDR",
            "is_recommended": true,
            "standard": {
              "id": "01982ded-f1e4-65b4-9a61-a18c80a6d6c1",
              "price": 62000,
              "discounted_price": 62000,
              "discount_percentage": null
            },
            "premium": null
          },
          {
            "currency_code": "USD",
            "is_recommended": true,
            "standard": {
              "id": "01982ded-f1e4-65b4-9a61-a18c80a6d6c1",
              "price": 4.5,
              "discounted_price": 4.5,
              "discount_percentage": null
            },
            "premium": null
          }
        ],
        "is_recommended": true,
        "standard": {
          "id": "01982ded-f1e4-65b4-9a61-a18c80a6d6c1",
          "currency_code": "IDR",
          "price": 62000,
          "discounted_price": 62000,
          "discount_percentage": null
        },
        "premium": null
      },
      {
        "natural_name": "Singapore 30D 10GB",
        "validity_days": 30,
        "data_type": "limited",
        "quota_in_gb": 10,
        "prices": [
          {
            "currency_code": "IDR",
            "is_recommended": false,
            "standard": {
              "id": "01982ded-f1d8-60f3-7bde-fe5cd1f01f44",
              "price": 175000,
              "discounted_price": 175000,
              "discount_percentage": null
            },
            "premium": null
          },
          {
            "currency_code": "USD",
            "is_recommended": false,
            "standard": {
              "id": "01982ded-f1d8-60f3-7bde-fe5cd1f01f44",
              "price": 12,
              "discounted_price": 12,
              "discount_percentage": null
            },
            "premium": null
          }
        ],
        "is_recommended": false,
        "standard": {
          "id": "01982ded-f1d8-60f3-7bde-fe5cd1f01f44",
          "currency_code": "IDR",
          "price": 175000,
          "discounted_price": 175000,
          "discount_percentage": null
        },
        "premium": null
      },
      {
        "natural_name": "Singapore 01D FUP1GB PRO",
        "validity_days": 1,
        "data_type": "unlimited",
        "quota_in_gb": 1,
        "prices": [
          {
            "currency_code": "IDR",
            "is_recommended": false,
            "standard": {
              "id": "01982ded-f1e9-e561-86ea-242a163670c0",
              "price": 25000,
              "discounted_price": 25000,
              "discount_percentage": null
            },
            "premium": null
          },
          {
            "currency_code": "USD",
            "is_recommended": false,
            "standard": {
              "id": "01982ded-f1e9-e561-86ea-242a163670c0",
              "price": 2.5,
              "discounted_price": 2.5,
              "discount_percentage": null
            },
            "premium": null
          }
        ],
        "is_recommended": false,
        "standard": {
          "id": "01982ded-f1e9-e561-86ea-242a163670c0",
          "currency_code": "IDR",
          "price": 25000,
          "discounted_price": 25000,
          "discount_percentage": null
        },
        "premium": null
      },
      {
        "natural_name": "Singapore 03D FUP1GB PRO",
        "validity_days": 3,
        "data_type": "unlimited",
        "quota_in_gb": 1,
        "prices": [
          {
            "currency_code": "IDR",
            "is_recommended": false,
            "standard": {
              "id": "01982ded-f1ea-454d-fbea-2a673d587799",
              "price": 54000,
              "discounted_price": 54000,
              "discount_percentage": null
            },
            "premium": null
          },
          {
            "currency_code": "USD",
            "is_recommended": false,
            "standard": {
              "id": "01982ded-f1ea-454d-fbea-2a673d587799",
              "price": 4.5,
              "discounted_price": 4.5,
              "discount_percentage": null
            },
            "premium": null
          }
        ],
        "is_recommended": false,
        "standard": {
          "id": "01982ded-f1ea-454d-fbea-2a673d587799",
          "currency_code": "IDR",
          "price": 54000,
          "discounted_price": 54000,
          "discount_percentage": null
        },
        "premium": null
      },
      {
        "natural_name": "Singapore 10D FUP1GB PRO",
        "validity_days": 10,
        "data_type": "unlimited",
        "quota_in_gb": 1,
        "prices": [
          {
            "currency_code": "IDR",
            "is_recommended": false,
            "standard": {
              "id": "01982ded-f1ec-7e5e-26dd-89a65cc7b5b3",
              "price": 131000,
              "discounted_price": 131000,
              "discount_percentage": null
            },
            "premium": null
          },
          {
            "currency_code": "USD",
            "is_recommended": false,
            "standard": {
              "id": "01982ded-f1ec-7e5e-26dd-89a65cc7b5b3",
              "price": 9.5,
              "discounted_price": 9.5,
              "discount_percentage": null
            },
            "premium": null
          }
        ],
        "is_recommended": false,
        "standard": {
          "id": "01982ded-f1ec-7e5e-26dd-89a65cc7b5b3",
          "currency_code": "IDR",
          "price": 131000,
          "discounted_price": 131000,
          "discount_percentage": null
        },
        "premium": null
      },
      {
        "natural_name": "Singapore 01D FUP2GB ELITE",
        "validity_days": 1,
        "data_type": "unlimited",
        "quota_in_gb": 2,
        "prices": [
          {
            "currency_code": "IDR",
            "is_recommended": false,
            "standard": {
              "id": "01982ded-f1ef-2a5a-cd87-11eaf5dee05b",
              "price": 30000,
              "discounted_price": 30000,
              "discount_percentage": null
            },
            "premium": null
          },
          {
            "currency_code": "USD",
            "is_recommended": false,
            "standard": {
              "id": "01982ded-f1ef-2a5a-cd87-11eaf5dee05b",
              "price": 3,
              "discounted_price": 3,
              "discount_percentage": null
            },
            "premium": null
          }
        ],
        "is_recommended": false,
        "standard": {
          "id": "01982ded-f1ef-2a5a-cd87-11eaf5dee05b",
          "currency_code": "IDR",
          "price": 30000,
          "discounted_price": 30000,
          "discount_percentage": null
        },
        "premium": null
      },
      {
        "natural_name": "Singapore 03D FUP2GB ELITE",
        "validity_days": 3,
        "data_type": "unlimited",
        "quota_in_gb": 2,
        "prices": [
          {
            "currency_code": "IDR",
            "is_recommended": false,
            "standard": {
              "id": "01982ded-f1f0-d558-850b-8cc790801b71",
              "price": 71000,
              "discounted_price": 71000,
              "discount_percentage": null
            },
            "premium": null
          },
          {
            "currency_code": "USD",
            "is_recommended": false,
            "standard": {
              "id": "01982ded-f1f0-d558-850b-8cc790801b71",
              "price": 5,
              "discounted_price": 5,
              "discount_percentage": null
            },
            "premium": null
          }
        ],
        "is_recommended": false,
        "standard": {
          "id": "01982ded-f1f0-d558-850b-8cc790801b71",
          "currency_code": "IDR",
          "price": 71000,
          "discounted_price": 71000,
          "discount_percentage": null
        },
        "premium": null
      },
      {
        "natural_name": "Singapore 01D 01GB",
        "validity_days": 1,
        "data_type": "limited",
        "quota_in_gb": 1,
        "prices": [
          {
            "currency_code": "IDR",
            "is_recommended": true,
            "standard": {
              "id": "01982ded-f1c7-1714-5072-41c346042637",
              "price": 23000,
              "discounted_price": 23000,
              "discount_percentage": null
            },
            "premium": null
          },
          {
            "currency_code": "USD",
            "is_recommended": true,
            "standard": {
              "id": "01982ded-f1c7-1714-5072-41c346042637",
              "price": 2,
              "discounted_price": 2,
              "discount_percentage": null
            },
            "premium": null
          }
        ],
        "is_recommended": true,
        "standard": {
          "id": "01982ded-f1c7-1714-5072-41c346042637",
          "currency_code": "IDR",
          "price": 23000,
          "discounted_price": 23000,
          "discount_percentage": null
        },
        "premium": null
      },
      {
        "natural_name": "Singapore 03D 03GB",
        "validity_days": 3,
        "data_type": "limited",
        "quota_in_gb": 3,
        "prices": [
          {
            "currency_code": "IDR",
            "is_recommended": true,
            "standard": {
              "id": "01982ded-f1ca-46c7-1714-80a1796876cd",
              "price": 50000,
              "discounted_price": 50000,
              "discount_percentage": null
            },
            "premium": null
          },
          {
            "currency_code": "USD",
            "is_recommended": true,
            "standard": {
              "id": "01982ded-f1ca-46c7-1714-80a1796876cd",
              "price": 4,
              "discounted_price": 4,
              "discount_percentage": null
            },
            "premium": null
          }
        ],
        "is_recommended": true,
        "standard": {
          "id": "01982ded-f1ca-46c7-1714-80a1796876cd",
          "currency_code": "IDR",
          "price": 50000,
          "discounted_price": 50000,
          "discount_percentage": null
        },
        "premium": null
      },
      {
        "natural_name": "Singapore 07D 05GB",
        "validity_days": 7,
        "data_type": "limited",
        "quota_in_gb": 5,
        "prices": [
          {
            "currency_code": "IDR",
            "is_recommended": true,
            "standard": {
              "id": "01982ded-f1cf-2659-b216-e7303731e066",
              "price": 75000,
              "discounted_price": 75000,
              "discount_percentage": null
            },
            "premium": null
          },
          {
            "currency_code": "USD",
            "is_recommended": true,
            "standard": {
              "id": "01982ded-f1cf-2659-b216-e7303731e066",
              "price": 5.5,
              "discounted_price": 5.5,
              "discount_percentage": null
            },
            "premium": null
          }
        ],
        "is_recommended": true,
        "standard": {
          "id": "01982ded-f1cf-2659-b216-e7303731e066",
          "currency_code": "IDR",
          "price": 75000,
          "discounted_price": 75000,
          "discount_percentage": null
        },
        "premium": null
      },
      {
        "natural_name": "Singapore 10D 05GB",
        "validity_days": 10,
        "data_type": "limited",
        "quota_in_gb": 5,
        "prices": [
          {
            "currency_code": "IDR",
            "is_recommended": true,
            "standard": {
              "id": "01982ded-f1d0-b39c-ea92-75e59cec7fae",
              "price": 93000,
              "discounted_price": 93000,
              "discount_percentage": null
            },
            "premium": null
          },
          {
            "currency_code": "USD",
            "is_recommended": true,
            "standard": {
              "id": "01982ded-f1d0-b39c-ea92-75e59cec7fae",
              "price": 6.5,
              "discounted_price": 6.5,
              "discount_percentage": null
            },
            "premium": null
          }
        ],
        "is_recommended": true,
        "standard": {
          "id": "01982ded-f1d0-b39c-ea92-75e59cec7fae",
          "currency_code": "IDR",
          "price": 93000,
          "discounted_price": 93000,
          "discount_percentage": null
        },
        "premium": null
      },
      {
        "natural_name": "Singapore 15D 10GB",
        "validity_days": 15,
        "data_type": "limited",
        "quota_in_gb": 10,
        "prices": [
          {
            "currency_code": "IDR",
            "is_recommended": true,
            "standard": {
              "id": "01982ded-f1d7-c9ec-7c93-d3357432b9fd",
              "price": 145000,
              "discounted_price": 145000,
              "discount_percentage": null
            },
            "premium": null
          },
          {
            "currency_code": "USD",
            "is_recommended": true,
            "standard": {
              "id": "01982ded-f1d7-c9ec-7c93-d3357432b9fd",
              "price": 10,
              "discounted_price": 10,
              "discount_percentage": null
            },
            "premium": null
          }
        ],
        "is_recommended": true,
        "standard": {
          "id": "01982ded-f1d7-c9ec-7c93-d3357432b9fd",
          "currency_code": "IDR",
          "price": 145000,
          "discounted_price": 145000,
          "discount_percentage": null
        },
        "premium": null
      }
    ],
    "coverages": {
      "standard": [
        {
          "id": "01911212-851c-a91a-9301-61f55988790b",
          "name": "Singapore",
          "name_id": "Singapura",
          "code_iso_2": "SG",
          "code_iso_3": "SGP",
          "networks": [
            {
              "id": "01982df3-341a-224b-e6b4-4ae4209223e6",
              "name": "Singtel",
              "support_4g_lte": true,
              "support_5g": true,
              "support_3g": true,
              "support_2g": false
            }
          ]
        }
      ],
      "premium": [
        {
          "id": "01911212-851c-a91a-9301-61f55988790b",
          "name": "Singapore",
          "name_id": "Singapura",
          "code_iso_2": "SG",
          "code_iso_3": "SGP",
          "networks": []
        }
      ]
    }
  }
}
